pydescriptors/__init__.py
pydescriptors/main.py
pydescriptors-1.2.2.dist-info/METADATA
pydescriptors-1.2.2.dist-info/WHEEL
pydescriptors-1.2.2.dist-info/top_level.txt
pydescriptors-1.2.2.dist-info/RECORD
