Metadata-Version: 2.1
Name: pydescriptors
Version: 1.2.2
Summary: A package with several simple descriptors
Home-page: https://github.com/Chebotarev-Alexey/PyDescriptors
Author: Alexey-Chebotarev
Classifier: Programming Language :: Python :: 3
Classifier: License :: OSI Approved :: MIT License
Classifier: Operating System :: OS Independent
Requires-Python: >=3.6
